semantic_version_inator/__init__.py
semantic_version_inator/console.py
semantic_version_inator/next_semantic_version.py
semantic_version_inator-0.0.2.dist-info/LICENSE
semantic_version_inator-0.0.2.dist-info/METADATA
semantic_version_inator-0.0.2.dist-info/WHEEL
semantic_version_inator-0.0.2.dist-info/entry_points.txt
semantic_version_inator-0.0.2.dist-info/top_level.txt
semantic_version_inator-0.0.2.dist-info/RECORD
