Metadata-Version: 2.1
Name: semantic-version-inator
Version: 0.0.2
Summary: Utility to aid in incrementing the semantic version of a Python package in an automated build
License: Apache License 2.0
Classifier: License :: OSI Approved :: Apache Software License
Requires-Python: >=3.10
License-File: LICENSE
